wapi/__init__.py
wapi/errors.py
wapi/main.py
wapi/auth/__init__.py
wapi/auth/auth_module.py
wapi/auth/auth_settings.py
wapi/tests/__init__.py
wapi/tests/test_cfg.py
wapi/tests/witclient_tester.py
wapi/tests/witserver_tester.py
witapi/__init__.py
witapi/errors.py
witapi/functions.py
witapi/main.py
witapi/methods.py
witapi/auth/__init__.py
witapi/auth/auth_module.py
witapi/auth/auth_settings.py
witapi/tests/__init__.py
witapi/tests/auth_test.py
witapi/tests/test_cfg.py
witapi/tests/transfer_test.py
witapi/tests/witclient_tester.py
witapi/tests/witserver_tester.py
witapi/tests/testa/__init__.py
witapi/tests/testa/clients.py
witapi/tests/testa/ser.py
witapi-3.33.dist-info/LICENSE
witapi-3.33.dist-info/METADATA
witapi-3.33.dist-info/WHEEL
witapi-3.33.dist-info/top_level.txt
witapi-3.33.dist-info/RECORD
